tcex_cli/__init__.py
tcex_cli/__metadata__.py
tcex_cli/registry.py
tcex_cli/app/__init__.py
tcex_cli/app/app.py
tcex_cli/app/config/__init__.py
tcex_cli/app/config/app_spec_yml.py
tcex_cli/app/config/install_json.py
tcex_cli/app/config/install_json_update.py
tcex_cli/app/config/install_json_validate.py
tcex_cli/app/config/job_json.py
tcex_cli/app/config/layout_json.py
tcex_cli/app/config/permutation.py
tcex_cli/app/config/tcex_json.py
tcex_cli/app/config/tcex_json_update.py
tcex_cli/app/config/model/__init__.py
tcex_cli/app/config/model/app_spec_yml_model.py
tcex_cli/app/config/model/install_json_model.py
tcex_cli/app/config/model/job_json_model.py
tcex_cli/app/config/model/layout_json_model.py
tcex_cli/app/config/model/tcex_json_model.py
tcex_cli/cli/__init__.py
tcex_cli/cli/cli.py
tcex_cli/cli/cli_abc.py
tcex_cli/cli/deploy/__init__.py
tcex_cli/cli/deploy/deploy.py
tcex_cli/cli/deploy/deploy_cli.py
tcex_cli/cli/deps/__init__.py
tcex_cli/cli/deps/deps.py
tcex_cli/cli/deps/deps_cli.py
tcex_cli/cli/migrate/__init__.py
tcex_cli/cli/migrate/migrate.py
tcex_cli/cli/migrate/migrate_cli.py
tcex_cli/cli/model/__init__.py
tcex_cli/cli/model/app_metadata_model.py
tcex_cli/cli/model/file_metadata_model.py
tcex_cli/cli/model/key_value_model.py
tcex_cli/cli/model/validation_data_model.py
tcex_cli/cli/package/__init__.py
tcex_cli/cli/package/package.py
tcex_cli/cli/package/package_cli.py
tcex_cli/cli/run/__init__.py
tcex_cli/cli/run/launch_abc.py
tcex_cli/cli/run/launch_organization.py
tcex_cli/cli/run/launch_playbook.py
tcex_cli/cli/run/launch_service_api.py
tcex_cli/cli/run/launch_service_common_abc.py
tcex_cli/cli/run/launch_service_common_trigger_abc.py
tcex_cli/cli/run/launch_service_custom_trigger.py
tcex_cli/cli/run/launch_service_webhook_trigger.py
tcex_cli/cli/run/playbook_create.py
tcex_cli/cli/run/request_handler_api.py
tcex_cli/cli/run/request_handler_webhook.py
tcex_cli/cli/run/run.py
tcex_cli/cli/run/run_cli.py
tcex_cli/cli/run/web_server.py
tcex_cli-1.0.5.dist-info/METADATA
tcex_cli-1.0.5.dist-info/WHEEL
tcex_cli-1.0.5.dist-info/entry_points.txt
tcex_cli-1.0.5.dist-info/top_level.txt
tcex_cli-1.0.5.dist-info/RECORD
