Metadata-Version: 2.2
Name: tcex_cli
Version: 1.0.5
Summary: ThreatConnect Exchange App CLI Tool
Author-email: ThreatConnect <support@threatconnect.com>
License: Apache-2.0
Project-URL: Documentation, https://github.com/ThreatConnect-Inc/tcex-cli
Project-URL: Source, https://github.com/ThreatConnect-Inc/tcex-cli
Keywords: tcex,threatconnect
Classifier: Development Status :: 5 - Production/Stable
Classifier: Intended Audience :: Developers
Classifier: Natural Language :: English
Classifier: License :: OSI Approved :: Apache Software License
Classifier: Operating System :: OS Independent
Classifier: Programming Language :: Python
Classifier: Programming Language :: Python :: 3.11
Classifier: Programming Language :: Python :: Implementation :: CPython
Classifier: Programming Language :: Python :: Implementation :: PyPy
Classifier: Topic :: Security
Requires-Python: >=3.11
Requires-Dist: arrow>=1.3.0
Requires-Dist: black>=25.1.0
Requires-Dist: debugpy>=1.8.12
Requires-Dist: fakeredis>=2.27.0
Requires-Dist: inflection>=0.5.1
Requires-Dist: isort>=6.0.0
Requires-Dist: jmespath>=1.0.1
Requires-Dist: paho-mqtt<2.0.0
Requires-Dist: pyaes>=1.6.1
Requires-Dist: pydantic<2.0.0
Requires-Dist: python-dateutil>=2.9.0
Requires-Dist: python-dotenv>=1.0.1
Requires-Dist: pyyaml>=6.0.2
Requires-Dist: redis<5.0.0
Requires-Dist: requests>=2.32.3
Requires-Dist: rich>=13.9.4
Requires-Dist: semantic-version>=2.10.0
Requires-Dist: tinydb>=4.8.2
Requires-Dist: typer>=0.15.1
